perfectns/__init__.py
perfectns/_version.py
perfectns/cached_gaussian_prior.py
perfectns/estimators.py
perfectns/likelihoods.py
perfectns/maths_functions.py
perfectns/nested_sampling.py
perfectns/plots.py
perfectns/priors.py
perfectns/results_tables.py
perfectns/settings.py
perfectns-2.1.3.dist-info/LICENSE
perfectns-2.1.3.dist-info/METADATA
perfectns-2.1.3.dist-info/WHEEL
perfectns-2.1.3.dist-info/top_level.txt
perfectns-2.1.3.dist-info/RECORD
