Metadata-Version: 2.1
Name: perfectns
Version: 2.1.3
Summary: Dynamic and standard nested sampling for spherically symmetric likelihoods and priors.
Home-page: https://github.com/ejhigson/perfectns
Author: Edward Higson
Author-email: e.higson@mrao.cam.ac.uk
License: MIT
Project-URL: Docs, http://perfectns.readthedocs.io/en/latest/
Keywords: nested-sampling dynamic-nested-sampling
Platform: UNKNOWN
Classifier: Development Status :: 5 - Production/Stable
Classifier: Intended Audience :: Science/Research
Classifier: License :: OSI Approved :: MIT License
Classifier: Programming Language :: Python :: 3
Classifier: Programming Language :: Python :: 3.5
Classifier: Programming Language :: Python :: 3.6
Classifier: Topic :: Scientific/Engineering :: Astronomy
Classifier: Topic :: Scientific/Engineering :: Physics
Classifier: Topic :: Scientific/Engineering :: Visualization
Classifier: Topic :: Scientific/Engineering :: Information Analysis
Requires-Dist: numpy (>=1.13)
Requires-Dist: scipy (>=1.0.0)
Requires-Dist: pandas
Requires-Dist: matplotlib (>=2.1.0)
Requires-Dist: mpmath
Requires-Dist: nestcheck (>=0.1.2)
Provides-Extra: docs
Requires-Dist: sphinx ; extra == 'docs'
Requires-Dist: numpydoc ; extra == 'docs'
Requires-Dist: sphinx-rtd-theme ; extra == 'docs'
Requires-Dist: nbsphinx (>=0.3.3) ; extra == 'docs'
